ycbev.py
ycbev_toolkit-1.1.0.dist-info/METADATA
ycbev_toolkit-1.1.0.dist-info/WHEEL
ycbev_toolkit-1.1.0.dist-info/top_level.txt
ycbev_toolkit-1.1.0.dist-info/RECORD
