Metadata-Version: 2.4
Name: ycbev_toolkit
Version: 1.1.0
Summary: A Python toolkit for loading and processing event data from the YCB-Ev dataset.
Home-page: https://github.com/paroj/ycbev
Author: Pavel Rojtberg
License: MIT
Requires-Dist: zstandard
Requires-Dist: numpy
Dynamic: author
Dynamic: description
Dynamic: description-content-type
Dynamic: home-page
Dynamic: license
Dynamic: requires-dist
Dynamic: summary
